{
    "__comment": "Model generated using MrCrayfish's Model Creator (https://mrcrayfish.com/tools?id=mc)",
    "textures": {
        "wire": "bagels_baking:block/trellis_wire",
        "wood": "minecraft:block/oak_log"
    },
    "display": {
        "gui": {
            "rotation": [ 30, 225, 0 ],
            "translation": [ -3, 1, -3 ],
            "scale": [ 0.625, 0.625, 0.625 ]
        },
        "ground": {
            "rotation": [ 0, 0, 0 ],
            "translation": [ 0, 3, 1.5 ],
            "scale": [ 0.25, 0.25, 0.25 ]
        },
        "fixed": {
            "rotation": [ 0, 0, 0 ],
            "translation": [ 0, 0, 3],
            "scale":[ 0.5, 0.5, 0.5 ]
        },
        "head": {
            "rotation": [ 0, 180, 0 ],
            "translation": [ 0, 0, 0 ],
            "scale": [ 1, 1, 1 ]
        },
        "firstperson_righthand": {
            "rotation": [ 0, 135, 0 ],
            "translation": [ 0, 2.5, 0 ],
            "scale": [ 0.4, 0.4, 0.4 ]
        },
        "thirdperson_righthand": {
            "rotation": [ 75, 135, 0 ],
            "translation": [ 0, 2.5, 0 ],
            "scale": [ 0.375, 0.375, 0.375 ]
        }
    },
    "elements": [
        {
            "name": "Post",
            "from": [ 6, 0, 0 ], 
            "to": [ 10, 16, 4 ], 
            "faces": {
                "north": { "texture": "#wood", "uv": [ 0, 0, 4, 16 ] },
                "east": { "texture": "#wood", "uv": [ 2, 0, 6, 16 ] },
                "south": { "texture": "#wood", "uv": [ 4, 0, 8, 16 ] },
                "west": { "texture": "#wood", "uv": [ 6, 0, 10, 16 ] },
                "up": { "texture": "#wood", "uv": [ 2, 0, 6, 4 ] },
                "down": { "texture": "#wood", "uv": [ 4, 4, 8, 8 ], "cullface": "down" }
            }
        },
        {
            "name": "Wire",
            "from": [ 10, 3, 0 ], 
            "to": [ 16, 4, 1 ], 
            "faces": {
                "north": { "texture": "#wire", "uv": [ 3, 0, 9, 1 ] },
                "east": { "texture": "#wire", "uv": [ 7, 0, 8, 1 ], "cullface": "east" },
                "south": { "texture": "#wire", "uv": [ 4, 0, 10, 1 ] },
                "up": { "texture": "#wire", "uv": [ 5, 0, 11, 1 ] },
                "down": { "texture": "#wire", "uv": [ 9, 0, 15, 1 ] }
            }
        },
        {
            "name": "Wire",
            "from": [ 10, 12, 0 ], 
            "to": [ 16, 13, 1 ], 
            "faces": {
                "north": { "texture": "#wire", "uv": [ 3, 0, 9, 1 ] },
                "east": { "texture": "#wire", "uv": [ 10, 0, 11, 1 ], "cullface": "east" },
                "south": { "texture": "#wire", "uv": [ 2, 0, 8, 1 ] },
                "up": { "texture": "#wire", "uv": [ 1, 0, 7, 1 ] },
                "down": { "texture": "#wire", "uv": [ 4, 0, 10, 1 ] }
            }
        },
        {
            "name": "Wire",
            "from": [ 0, 12, 0 ], 
            "to": [ 6, 13, 1 ], 
            "faces": {
                "north": { "texture": "#wire", "uv": [ 3, 0, 9, 1 ] },
                "south": { "texture": "#wire", "uv": [ 4, 0, 10, 1 ] },
                "west": { "texture": "#wire", "uv": [ 7, 0, 8, 1 ], "cullface": "west" },
                "up": { "texture": "#wire", "uv": [ 5, 0, 11, 1 ] },
                "down": { "texture": "#wire", "uv": [ 9, 0, 15, 1 ] }
            }
        },
        {
            "name": "Wire",
            "from": [ 0, 3, 0 ], 
            "to": [ 6, 4, 1 ], 
            "faces": {
                "north": { "texture": "#wire", "uv": [ 2, 0, 8, 1 ] },
                "south": { "texture": "#wire", "uv": [ 1, 0, 7, 1 ] },
                "west": { "texture": "#wire", "uv": [ 8, 0, 9, 1 ], "cullface": "west" },
                "up": { "texture": "#wire", "uv": [ 3, 0, 9, 1 ] },
                "down": { "texture": "#wire", "uv": [ 2, 0, 8, 1 ] }
            }
        }
    ]
}